nat/meta/pypi.md
nat/plugins/agno/__init__.py
nat/plugins/agno/llm.py
nat/plugins/agno/register.py
nat/plugins/agno/tool_wrapper.py
nat/plugins/agno/tools/__init__.py
nat/plugins/agno/tools/register.py
nat/plugins/agno/tools/serp_api_tool.py
nvidia_nat_agno-1.3.1.dist-info/licenses/LICENSE-3rd-party.txt
nvidia_nat_agno-1.3.1.dist-info/licenses/LICENSE.md
nvidia_nat_agno-1.3.1.dist-info/METADATA
nvidia_nat_agno-1.3.1.dist-info/WHEEL
nvidia_nat_agno-1.3.1.dist-info/entry_points.txt
nvidia_nat_agno-1.3.1.dist-info/top_level.txt
nvidia_nat_agno-1.3.1.dist-info/RECORD
